snakemake_executor_plugin_cluster_generic/__init__.py
snakemake_executor_plugin_cluster_generic-1.0.8.dist-info/LICENSE
snakemake_executor_plugin_cluster_generic-1.0.8.dist-info/METADATA
snakemake_executor_plugin_cluster_generic-1.0.8.dist-info/WHEEL
snakemake_executor_plugin_cluster_generic-1.0.8.dist-info/RECORD
